feather_tools/__init__.py
feather_tools/csv2f.py
feather_tools/f2csv.py
feather_tools/fless.py
feather_tools/ftail.py
feather_tools/ftools_workhorse.py
feather_tools/fwc.py
feather_tools/test/__init__.py
feather_tools/test/csv2f_copy.py
feather_tools/test/f2csv_copy.py
feather_tools/test/fless_copy.py
feather_tools/test/ftail_copy.py
feather_tools/test/fwc_copy.py
feather_tools/test/simple_feather.feather
feather_tools/test/test_ftools_workhorse.py
feather_tools-1.1.0.dist-info/METADATA
feather_tools-1.1.0.dist-info/WHEEL
feather_tools-1.1.0.dist-info/entry_points.txt
feather_tools-1.1.0.dist-info/top_level.txt
feather_tools-1.1.0.dist-info/RECORD
