Metadata-Version: 2.4
Name: feather_tools
Version: 1.1.0
Summary: Scripts to use for pyarrow feather files in a Linux terminal window
Author-email: Andreas Paepcke <paepcke@cs.stanford.edu>
Maintainer-email: Andreas Paepcke <paepcke@cs.stanford.edu>
License: MIT License
Project-URL: Homepage, https://github.com/paepcke/feather-tools
Project-URL: Documentation, https://github.com/paepcke/feather-tools
Requires-Python: >=3.11
Requires-Dist: pandas>=2.2.2
Requires-Dist: pyarrow>=16.0.0
Provides-Extra: test
Requires-Dist: pytest; extra == "test"
